figma_mcp/__init__.py
figma_mcp/clean_node.py
figma_mcp/main.py
iflow_mcp_figma_mcp-0.1.3.dist-info/licenses/LICENSE
iflow_mcp_figma_mcp-0.1.3.dist-info/METADATA
iflow_mcp_figma_mcp-0.1.3.dist-info/WHEEL
iflow_mcp_figma_mcp-0.1.3.dist-info/entry_points.txt
iflow_mcp_figma_mcp-0.1.3.dist-info/top_level.txt
iflow_mcp_figma_mcp-0.1.3.dist-info/RECORD
